xrpc/__init__.py
xrpc/abstract.py
xrpc/client.py
xrpc/const.py
xrpc/dict.py
xrpc/dsl.py
xrpc/error.py
xrpc/logging.py
xrpc/net.py
xrpc/popen.py
xrpc/runtime.py
xrpc/server.py
xrpc/service.py
xrpc/transform.py
xrpc/transport.py
xrpc/util.py
xrpc/examples/__init__.py
xrpc/examples/cli.py
xrpc/examples/cli2.py
xrpc/examples/exemplary_rpc.py
xrpc/impl/__init__.py
xrpc/impl/broker.py
xrpc/serde/__init__.py
xrpc/serde/abstract.py
xrpc/serde/types.py
xrpc-0.0.1a0.dist-info/METADATA
xrpc-0.0.1a0.dist-info/RECORD
xrpc-0.0.1a0.dist-info/WHEEL
xrpc-0.0.1a0.dist-info/top_level.txt
