Metadata-Version: 2.1
Name: xrpc
Version: 0.0.1a0
Summary: Python 3 type hinted protobuf binding generator
Home-page: https://github.com/andreycizov/python-xrpc
Author: Andrey Cizov
Author-email: acizov@gmail.com
License: UNKNOWN
Platform: UNKNOWN
Classifier: Development Status :: 2 - Pre-Alpha
Classifier: Intended Audience :: Developers
Classifier: License :: OSI Approved :: Apache Software License
Classifier: Natural Language :: English
Classifier: Programming Language :: Python :: 3.6
Requires-Dist: pytz
